latex_tools_101/__init__.py
latex_tools_101/latex_generators.py
latex_tools_101-0.4.dist-info/METADATA
latex_tools_101-0.4.dist-info/WHEEL
latex_tools_101-0.4.dist-info/top_level.txt
latex_tools_101-0.4.dist-info/RECORD
