Metadata-Version: 2.4
Name: latex_tools_101
Version: 0.4
Summary: Small lib with tools for Latex
Dynamic: summary
